dlogger.py
dlogger-1.0.5.dist-info/licenses/LICENSE
dlogger-1.0.5.dist-info/METADATA
dlogger-1.0.5.dist-info/WHEEL
dlogger-1.0.5.dist-info/top_level.txt
dlogger-1.0.5.dist-info/RECORD
