Metadata-Version: 2.4
Name: dlogger
Version: 1.0.5
Summary: Dynamic Console Logger for Python with colored output, custom icons, and other features.
Home-page: https://github.com/dpipstudio/dlogger
Author: Douxxtech
Author-email: douxx@douxx.tech
License: GPL-3.0
Classifier: Development Status :: 5 - Production/Stable
Classifier: Intended Audience :: Developers
Classifier: Topic :: Software Development :: Libraries
Classifier: License :: OSI Approved :: GNU General Public License v3 (GPLv3)
Classifier: Programming Language :: Python :: 3
Classifier: Operating System :: OS Independent
Requires-Python: >=3.6
License-File: LICENSE
Dynamic: license-file
